drfmockresponse/__init__.py
drfmockresponse/admin.py
drfmockresponse/apps.py
drfmockresponse/content_types.py
drfmockresponse/http_codes.py
drfmockresponse/http_headers.py
drfmockresponse/middleware.py
drfmockresponse/migrations/0001_initial.py
drfmockresponse/migrations/__init__.py
drfmockresponse/models.py
drfmockresponse-0.1.4.dist-info/LICENSE
drfmockresponse-0.1.4.dist-info/METADATA
drfmockresponse-0.1.4.dist-info/WHEEL
drfmockresponse-0.1.4.dist-info/RECORD
