Metadata-Version: 2.3
Name: drfmockresponse
Version: 0.1.4
Summary: Middleware that can mock responses in Django Rest Framework.
Author: Kostas Konstantopoulos
Author-email: ntopoulos@yahoo.com
Requires-Python: >=3.10,<4.0
Classifier: Programming Language :: Python :: 3
Classifier: Programming Language :: Python :: 3.10
Classifier: Programming Language :: Python :: 3.11
Classifier: Programming Language :: Python :: 3.12
Classifier: Programming Language :: Python :: 3.13
Requires-Dist: django (>=5.2.6,<6.0.0)
Requires-Dist: djangorestframework (>=3.16.1,<4.0.0)
